siaextractlib/__init__.py
siaextractlib/extractors/__init__.py
siaextractlib/extractors/base_extractor.py
siaextractlib/extractors/interfaces.py
siaextractlib/extractors/motu.py
siaextractlib/extractors/opendap.py
siaextractlib/processing/__init__.py
siaextractlib/processing/parallelism.py
siaextractlib/processing/wrangling.py
siaextractlib/utils/__init__.py
siaextractlib/utils/auth.py
siaextractlib/utils/exceptions.py
siaextractlib/utils/log.py
siaextractlib/utils/metadata.py
siaextractlib-0.2.2.dist-info/LICENCE
siaextractlib-0.2.2.dist-info/METADATA
siaextractlib-0.2.2.dist-info/WHEEL
siaextractlib-0.2.2.dist-info/top_level.txt
siaextractlib-0.2.2.dist-info/RECORD
