Metadata-Version: 2.1
Name: siaextractlib
Version: 0.2.2
Summary: Provide an easy to use API for download oceanographic data.
Author: Alexis Montejo et al.
Maintainer: SIA Project
Project-URL: Homepage, https://sia-information-system.github.io/sia-website
Project-URL: Source Code, https://github.com/sia-information-system/siaextractlib
Keywords: gis,oceanographic,oceanic,etl,data,extraction
Requires-Python: >=3.10
License-File: LICENCE
Requires-Dist: xarray (>=2023.5.0)
Requires-Dist: netcdf4 (==1.6.2)
Requires-Dist: motuclient (>=3.0.0)
Requires-Dist: dask (>=2022.11.1)
Requires-Dist: cftime (>=1.6.2)
Requires-Dist: requests (>=2.28.2)
Requires-Dist: pydap (>=3.4.1)
Requires-Dist: WebOb (>=1.8.7)
Provides-Extra: dev
Requires-Dist: bumpver ; extra == 'dev'
Requires-Dist: build ; extra == 'dev'
Requires-Dist: twine ; extra == 'dev'
